urdupunjabilemma/BiLSTM.h5
urdupunjabilemma/__init__.py
urdupunjabilemma/tokenizer.pickle
urdupunjabilemma-0.2.dist-info/LICENSE.txt
urdupunjabilemma-0.2.dist-info/METADATA
urdupunjabilemma-0.2.dist-info/WHEEL
urdupunjabilemma-0.2.dist-info/top_level.txt
urdupunjabilemma-0.2.dist-info/RECORD
