Metadata-Version: 2.1
Name: urdupunjabilemma
Version: 0.2
Summary: This is Bilingual Lemmatizer for Urdu and Punjabi. This will generate lemma of the given word for both Urdu and Shahmukhi Punjabi.
Home-page: UNKNOWN
Author: Muhammad Umar, Malaika Basharat
Author-email: umarwaris450@gmail.com, malaikabdev@gmail.com
License: UNKNOWN
Platform: UNKNOWN
Classifier: Programming Language :: Python :: 3
Classifier: License :: OSI Approved :: MIT License
Classifier: Operating System :: OS Independent
Requires-Dist: numpy
Requires-Dist: tensorflow
Requires-Dist: keras
